<?xml version="1.0" ?>
<annotation>
<folder>widerface</folder>
<filename>2--Demonstration_2_Demonstration_Protesters_2_535.jpg</filename>
<source>
<database>wider face Database</database>
<annotation>PASCAL VOC2007</annotation>
<image>flickr</image>
<flickrid>-1</flickrid>
</source>
<owner>
<flickrid>yanyu</flickrid>
<name>yanyu</name>
</owner>
<size>
<width>1198</width>
<height>1199</height>
<depth>3</depth>
</size>
<segmented>0</segmented>
<object>
<name>face</name>
<pose>Unspecified</pose>
<truncated>1</truncated>
<difficult>0</difficult>
<bndbox>
<xmin>751</xmin>
<ymin>97</ymin>
<xmax>908</xmax>
<ymax>277</ymax>
</bndbox>
</object>
<object>
<name>face</name>
<pose>Unspecified</pose>
<truncated>1</truncated>
<difficult>0</difficult>
<bndbox>
<xmin>893</xmin>
<ymin>196</ymin>
<xmax>955</xmax>
<ymax>281</ymax>
</bndbox>
</object>
<object>
<name>face</name>
<pose>Unspecified</pose>
<truncated>1</truncated>
<difficult>0</difficult>
<bndbox>
<xmin>244</xmin>
<ymin>151</ymin>
<xmax>355</xmax>
<ymax>284</ymax>
</bndbox>
</object>
<object>
<name>face</name>
<pose>Unspecified</pose>
<truncated>1</truncated>
<difficult>0</difficult>
<bndbox>
<xmin>167</xmin>
<ymin>17</ymin>
<xmax>210</xmax>
<ymax>75</ymax>
</bndbox>
</object>
</annotation>
