<?xml version="1.0" ?>
<annotation>
<folder>widerface</folder>
<filename>23--Shoppers_23_Shoppers_Shoppers_23_26.jpg</filename>
<source>
<database>wider face Database</database>
<annotation>PASCAL VOC2007</annotation>
<image>flickr</image>
<flickrid>-1</flickrid>
</source>
<owner>
<flickrid>yanyu</flickrid>
<name>yanyu</name>
</owner>
<size>
<width>1024</width>
<height>1023</height>
<depth>3</depth>
</size>
<segmented>0</segmented>
<object>
<name>face</name>
<pose>Unspecified</pose>
<truncated>1</truncated>
<difficult>0</difficult>
<bndbox>
<xmin>431</xmin>
<ymin>219</ymin>
<xmax>481</xmax>
<ymax>331</ymax>
</bndbox>
</object>
<object>
<name>face</name>
<pose>Unspecified</pose>
<truncated>1</truncated>
<difficult>0</difficult>
<bndbox>
<xmin>701</xmin>
<ymin>171</ymin>
<xmax>744</xmax>
<ymax>274</ymax>
</bndbox>
</object>
<object>
<name>face</name>
<pose>Unspecified</pose>
<truncated>1</truncated>
<difficult>0</difficult>
<bndbox>
<xmin>198</xmin>
<ymin>226</ymin>
<xmax>238</xmax>
<ymax>306</ymax>
</bndbox>
</object>
<object>
<name>face</name>
<pose>Unspecified</pose>
<truncated>1</truncated>
<difficult>0</difficult>
<bndbox>
<xmin>980</xmin>
<ymin>239</ymin>
<xmax>1016</xmax>
<ymax>292</ymax>
</bndbox>
</object>
</annotation>
