<?xml version="1.0" ?>
<annotation>
<folder>widerface</folder>
<filename>33--Running_33_Running_Running_33_75.jpg</filename>
<source>
<database>wider face Database</database>
<annotation>PASCAL VOC2007</annotation>
<image>flickr</image>
<flickrid>-1</flickrid>
</source>
<owner>
<flickrid>yanyu</flickrid>
<name>yanyu</name>
</owner>
<size>
<width>1024</width>
<height>1024</height>
<depth>3</depth>
</size>
<segmented>0</segmented>
<object>
<name>face</name>
<pose>Unspecified</pose>
<truncated>1</truncated>
<difficult>0</difficult>
<bndbox>
<xmin>45</xmin>
<ymin>341</ymin>
<xmax>75</xmax>
<ymax>384</ymax>
</bndbox>
</object>
<object>
<name>face</name>
<pose>Unspecified</pose>
<truncated>1</truncated>
<difficult>0</difficult>
<bndbox>
<xmin>247</xmin>
<ymin>360</ymin>
<xmax>272</xmax>
<ymax>394</ymax>
</bndbox>
</object>
<object>
<name>face</name>
<pose>Unspecified</pose>
<truncated>1</truncated>
<difficult>0</difficult>
<bndbox>
<xmin>468</xmin>
<ymin>350</ymin>
<xmax>488</xmax>
<ymax>394</ymax>
</bndbox>
</object>
<object>
<name>face</name>
<pose>Unspecified</pose>
<truncated>1</truncated>
<difficult>0</difficult>
<bndbox>
<xmin>775</xmin>
<ymin>352</ymin>
<xmax>800</xmax>
<ymax>392</ymax>
</bndbox>
</object>
<object>
<name>face</name>
<pose>Unspecified</pose>
<truncated>1</truncated>
<difficult>0</difficult>
<bndbox>
<xmin>882</xmin>
<ymin>346</ymin>
<xmax>904</xmax>
<ymax>388</ymax>
</bndbox>
</object>
</annotation>
