<?xml version="1.0" ?>
<annotation>
<folder>widerface</folder>
<filename>35--Basketball_35_Basketball_basketballgame_ball_35_47.jpg</filename>
<source>
<database>wider face Database</database>
<annotation>PASCAL VOC2007</annotation>
<image>flickr</image>
<flickrid>-1</flickrid>
</source>
<owner>
<flickrid>yanyu</flickrid>
<name>yanyu</name>
</owner>
<size>
<width>1024</width>
<height>1024</height>
<depth>3</depth>
</size>
<segmented>0</segmented>
<object>
<name>face</name>
<pose>Unspecified</pose>
<truncated>1</truncated>
<difficult>0</difficult>
<bndbox>
<xmin>318</xmin>
<ymin>729</ymin>
<xmax>373</xmax>
<ymax>793</ymax>
</bndbox>
</object>
<object>
<name>face</name>
<pose>Unspecified</pose>
<truncated>1</truncated>
<difficult>0</difficult>
<bndbox>
<xmin>156</xmin>
<ymin>646</ymin>
<xmax>183</xmax>
<ymax>676</ymax>
</bndbox>
</object>
<object>
<name>face</name>
<pose>Unspecified</pose>
<truncated>1</truncated>
<difficult>0</difficult>
<bndbox>
<xmin>572</xmin>
<ymin>724</ymin>
<xmax>604</xmax>
<ymax>769</ymax>
</bndbox>
</object>
<object>
<name>face</name>
<pose>Unspecified</pose>
<truncated>1</truncated>
<difficult>0</difficult>
<bndbox>
<xmin>678</xmin>
<ymin>782</ymin>
<xmax>727</xmax>
<ymax>871</ymax>
</bndbox>
</object>
</annotation>
