<?xml version="1.0" ?>
<annotation>
<folder>widerface</folder>
<filename>39--Ice_Skating_39_Ice_Skating_iceskiing_39_138.jpg</filename>
<source>
<database>wider face Database</database>
<annotation>PASCAL VOC2007</annotation>
<image>flickr</image>
<flickrid>-1</flickrid>
</source>
<owner>
<flickrid>yanyu</flickrid>
<name>yanyu</name>
</owner>
<size>
<width>1024</width>
<height>1024</height>
<depth>3</depth>
</size>
<segmented>0</segmented>
<object>
<name>face</name>
<pose>Unspecified</pose>
<truncated>1</truncated>
<difficult>0</difficult>
<bndbox>
<xmin>20</xmin>
<ymin>142</ymin>
<xmax>59</xmax>
<ymax>188</ymax>
</bndbox>
</object>
<object>
<name>face</name>
<pose>Unspecified</pose>
<truncated>1</truncated>
<difficult>0</difficult>
<bndbox>
<xmin>90</xmin>
<ymin>362</ymin>
<xmax>135</xmax>
<ymax>399</ymax>
</bndbox>
</object>
<object>
<name>face</name>
<pose>Unspecified</pose>
<truncated>1</truncated>
<difficult>0</difficult>
<bndbox>
<xmin>283</xmin>
<ymin>243</ymin>
<xmax>361</xmax>
<ymax>314</ymax>
</bndbox>
</object>
<object>
<name>face</name>
<pose>Unspecified</pose>
<truncated>1</truncated>
<difficult>0</difficult>
<bndbox>
<xmin>388</xmin>
<ymin>368</ymin>
<xmax>423</xmax>
<ymax>408</ymax>
</bndbox>
</object>
<object>
<name>face</name>
<pose>Unspecified</pose>
<truncated>1</truncated>
<difficult>0</difficult>
<bndbox>
<xmin>553</xmin>
<ymin>246</ymin>
<xmax>648</xmax>
<ymax>323</ymax>
</bndbox>
</object>
<object>
<name>face</name>
<pose>Unspecified</pose>
<truncated>1</truncated>
<difficult>0</difficult>
<bndbox>
<xmin>787</xmin>
<ymin>404</ymin>
<xmax>842</xmax>
<ymax>481</ymax>
</bndbox>
</object>
<object>
<name>face</name>
<pose>Unspecified</pose>
<truncated>1</truncated>
<difficult>0</difficult>
<bndbox>
<xmin>2</xmin>
<ymin>348</ymin>
<xmax>28</xmax>
<ymax>386</ymax>
</bndbox>
</object>
<object>
<name>face</name>
<pose>Unspecified</pose>
<truncated>1</truncated>
<difficult>0</difficult>
<bndbox>
<xmin>49</xmin>
<ymin>304</ymin>
<xmax>77</xmax>
<ymax>352</ymax>
</bndbox>
</object>
</annotation>
