<?xml version="1.0" ?>
<annotation>
<folder>widerface</folder>
<filename>39--Ice_Skating_39_Ice_Skating_iceskiing_39_52.jpg</filename>
<source>
<database>wider face Database</database>
<annotation>PASCAL VOC2007</annotation>
<image>flickr</image>
<flickrid>-1</flickrid>
</source>
<owner>
<flickrid>yanyu</flickrid>
<name>yanyu</name>
</owner>
<size>
<width>1024</width>
<height>1024</height>
<depth>3</depth>
</size>
<segmented>0</segmented>
<object>
<name>face</name>
<pose>Unspecified</pose>
<truncated>1</truncated>
<difficult>0</difficult>
<bndbox>
<xmin>513</xmin>
<ymin>405</ymin>
<xmax>536</xmax>
<ymax>439</ymax>
</bndbox>
</object>
<object>
<name>face</name>
<pose>Unspecified</pose>
<truncated>1</truncated>
<difficult>0</difficult>
<bndbox>
<xmin>775</xmin>
<ymin>668</ymin>
<xmax>814</xmax>
<ymax>720</ymax>
</bndbox>
</object>
<object>
<name>face</name>
<pose>Unspecified</pose>
<truncated>1</truncated>
<difficult>0</difficult>
<bndbox>
<xmin>224</xmin>
<ymin>368</ymin>
<xmax>249</xmax>
<ymax>405</ymax>
</bndbox>
</object>
<object>
<name>face</name>
<pose>Unspecified</pose>
<truncated>1</truncated>
<difficult>0</difficult>
<bndbox>
<xmin>222</xmin>
<ymin>587</ymin>
<xmax>251</xmax>
<ymax>636</ymax>
</bndbox>
</object>
<object>
<name>face</name>
<pose>Unspecified</pose>
<truncated>1</truncated>
<difficult>0</difficult>
<bndbox>
<xmin>476</xmin>
<ymin>596</ymin>
<xmax>506</xmax>
<ymax>637</ymax>
</bndbox>
</object>
<object>
<name>face</name>
<pose>Unspecified</pose>
<truncated>1</truncated>
<difficult>0</difficult>
<bndbox>
<xmin>170</xmin>
<ymin>343</ymin>
<xmax>217</xmax>
<ymax>376</ymax>
</bndbox>
</object>
</annotation>
